{
    "ede-trifecta-2.1": {
        "branch": "trifecta-2.1",
        "description": "Templating language with similar syntax and features to Liquid or Jinja2.",
        "homepage": "",
        "owner": "pbogdan",
        "repo": "ede",
        "rev": "1114be9457b15aa8f40a30e058b766048fe3479a",
        "sha256": "1km89ahwa4r2ly85kwzp6np807lf5n81bbbszk4yhqmx0qcxcmzg",
        "type": "tarball",
        "url": "https://github.com/pbogdan/ede/archive/1114be9457b15aa8f40a30e058b766048fe3479a.tar.gz",
        "url_template": "https://github.com/<owner>/<repo>/archive/<rev>.tar.gz"
    },
    "shell-cmd": {
        "branch": "master",
        "description": "Simple Haskell library for working with shell commands in a more convenient way.",
        "homepage": null,
        "owner": "pbogdan",
        "repo": "shell-cmd",
        "rev": "a15c2c0a9393be53da0a6a594c103dffca603348",
        "sha256": "0953hr87zrl2b7swvlncvmapifjn111z3zmhv9yb5x0mm01m99a9",
        "type": "tarball",
        "url": "https://github.com/pbogdan/shell-cmd/archive/a15c2c0a9393be53da0a6a594c103dffca603348.tar.gz",
        "url_template": "https://github.com/<owner>/<repo>/archive/<rev>.tar.gz"
    },
    "unstable": {
        "branch": "nixos-unstable",
        "description": "Nix Packages collection",
        "homepage": null,
        "owner": "NixOS",
        "repo": "nixpkgs",
        "rev": "c59ea8b8a0e7f927e7291c14ea6cd1bd3a16ff38",
        "sha256": "1ak7jqx94fjhc68xh1lh35kh3w3ndbadprrb762qgvcfb8351x8v",
        "type": "tarball",
        "url": "https://github.com/NixOS/nixpkgs/archive/c59ea8b8a0e7f927e7291c14ea6cd1bd3a16ff38.tar.gz",
        "url_template": "https://github.com/<owner>/<repo>/archive/<rev>.tar.gz"
    }
}
